{"cameraMode":{"drawMode":0,"name":"Shaded","section":"Shading Mode"},"sceneLighting":false,"audioPlay":false,"sceneViewState":{"showFog":true,"showMaterialUpdate":false,"showSkybox":false,"showFlares":true,"showImageEffects":true,"showParticleSystems":true},"in2DMode":false,"pivot":{"x":9.95617389678955,"y":-16.348888397216798,"z":20.326330184936525},"rotation":{"x":-0.07990743219852448,"y":0.24356676638126374,"z":0.02013998292386532,"w":0.9663769602775574},"size":18.965850830078126,"orthographic":false}