{"cameraMode":{"drawMode":0,"name":"Shaded","section":"Shading Mode"},"sceneLighting":true,"audioPlay":false,"sceneViewState":{"showFog":true,"showMaterialUpdate":false,"showSkybox":true,"showFlares":true,"showImageEffects":true,"showParticleSystems":true},"in2DMode":false,"pivot":{"x":37.215484619140628,"y":-31.16037368774414,"z":24.179513931274415},"rotation":{"x":0.15066319704055787,"y":0.08530274033546448,"z":-0.013050269335508347,"w":0.984811544418335},"size":69.95948028564453,"orthographic":false}